FFSeval/FFS.py
FFSeval/Kriging.py
FFSeval/Parse.py
FFSeval/__init__.py
FFSeval/data/J-1-b-1.csv
FFSeval/data/J-1-b-2.csv
FFSeval/data/J-1-b.csv
FFSeval/data/J-1-d.csv
FFSeval/data/J-2-a.csv
FFSeval/data/J-2-b.csv
FFSeval/data/J-2-f.csv
FFSeval/data/J-2-g-a.csv
FFSeval/data/J-2-g-b.csv
FFSeval/data/J-2-h.csv
FFSeval/data/J-2-k-a-1.csv
FFSeval/data/J-2-k-a-2.csv
FFSeval/data/J-2-k-b.csv
FFSeval/data/J-2-m.csv
FFSeval/data/J-7-a.csv
FFSeval/data/K-1-a-2.csv
FFSeval/data/K-1-a-3.csv
FFSeval/data/K-1-b-2.csv
FFSeval/data/K-1-c-2.csv
FFSeval/data/K-1-e-2-3-A.csv
FFSeval/data/K-1-e-2-3-B.csv
FFSeval/data/K-1-e-2.csv
FFSeval/data/K-2-a-1-F0A.csv
FFSeval/data/K-2-a-1-F0B.csv
FFSeval/data/K-2-a-1-F1A.csv
FFSeval/data/K-2-a-1-F1B.csv
FFSeval/data/K-2-a-1-F2A.csv
FFSeval/data/K-2-a-1-F2B.csv
FFSeval/data/K-2-a-1-F3A.csv
FFSeval/data/K-2-a-1-F3B.csv
FFSeval/data/K-2-a-1.csv
FFSeval/data/K-2-a-2-F0A.csv
FFSeval/data/K-2-a-2-F0B.csv
FFSeval/data/K-2-a-2-F1A.csv
FFSeval/data/K-2-a-2-F1B.csv
FFSeval/data/K-2-a-2-F2A.csv
FFSeval/data/K-2-a-2-F2B.csv
FFSeval/data/K-2-a-2-F3A.csv
FFSeval/data/K-2-a-2-F3B.csv
FFSeval/data/K-2-a-2.csv
FFSeval/data/K-2-b-1.csv
FFSeval/data/K-2-c-1-F0A.csv
FFSeval/data/K-2-c-1-F0B.csv
FFSeval/data/K-2-c-1-F1A.csv
FFSeval/data/K-2-c-1-F1B.csv
FFSeval/data/K-2-c-1-F2A.csv
FFSeval/data/K-2-c-1-F2B.csv
FFSeval/data/K-2-c-1-F3A.csv
FFSeval/data/K-2-c-1-F3B.csv
FFSeval/data/K-2-c-1.csv
FFSeval/data/K-2-d.csv
FFSeval/data/K-2-e-1.csv
FFSeval/data/K-2-e-3.csv
FFSeval/data/K-2-f-1.csv
FFSeval/data/K-2-f-2.csv
FFSeval/data/K-2-f-3.csv
FFSeval/data/K-2-h-1.csv
FFSeval/data/K-2-i-1.csv
FFSeval/data/K-2-i-2.csv
FFSeval/data/K-2-j.csv
FFSeval/data/K-2-k-1.csv
FFSeval/data/K-2-k-4.csv
FFSeval/data/K-3-a.csv
FFSeval/data/K-3-b-1.csv
FFSeval/data/K-3-c-1.csv
FFSeval/data/K-3-c-2.csv
FFSeval/data/K-3-c-3.csv
FFSeval/data/K-3-c.csv
FFSeval/data/K-4-a-1.csv
FFSeval/data/K-4-a-2.csv
FFSeval/data/K-4-b-1.csv
FFSeval/data/K-4-d.csv
FFSeval/data/K-5-b-1.csv
ffseval-1.0.8.dist-info/licenses/LICENSE
ffseval-1.0.8.dist-info/METADATA
ffseval-1.0.8.dist-info/WHEEL
ffseval-1.0.8.dist-info/top_level.txt
ffseval-1.0.8.dist-info/RECORD
