Metadata-Version: 2.4
Name: ffseval
Version: 1.0.8
Summary: Evaluation of fitness for service
Home-page: https://github.com/ShinsukeSakai0321/FFS
Author: Shinsuke Sakai
Author-email: sakaishin0321@gmail.com
License: MIT
Classifier: Programming Language :: Python :: 3
Classifier: License :: OSI Approved :: MIT License
Classifier: Operating System :: OS Independent
Requires-Python: >=3.6
License-File: LICENSE
Requires-Dist: numpy==1.26.4
Requires-Dist: scikit-learn
Requires-Dist: matplotlib
Requires-Dist: Kriging
Requires-Dist: typing
Dynamic: author
Dynamic: author-email
Dynamic: classifier
Dynamic: description
Dynamic: description-content-type
Dynamic: home-page
Dynamic: license
Dynamic: license-file
Dynamic: requires-dist
Dynamic: requires-python
Dynamic: summary
